observables/observable_generic.py
observables/observable_object.py
observables/py.typed
observables/typed_wrappers.py
observables-0.1.3.dist-info/METADATA
observables-0.1.3.dist-info/WHEEL
observables-0.1.3.dist-info/licenses/LICENSE
observables-0.1.3.dist-info/RECORD
