Metadata-Version: 2.4
Name: observables
Version: 0.1.3
Summary: Observable variables for Python, similar to Vue, Redux, etc.
License-File: LICENSE
Requires-Python: >=3.9
